g4f_xn/__init__.py
g4f_xn/gpt.py
g4f_xn/misc.py
g4f_xn/output.py
g4f_xn/sound.py
g4f_xn/test_providers.py
g4f_xn/sound/Hint.wav
g4f_xn/sound/__init__.py
g4f_xn/sound/coins.wav
g4f_xn/sound/metal-pipe.wav
g4f_xn/sound/sound.py
g4f_xn-0.0.6.dist-info/LICENSE
g4f_xn-0.0.6.dist-info/METADATA
g4f_xn-0.0.6.dist-info/WHEEL
g4f_xn-0.0.6.dist-info/top_level.txt
g4f_xn-0.0.6.dist-info/RECORD
